minipyparser/__init__.py
minipyparser/hook.py
minipyparser/parser.py
minipyparser/tokenizer.py
minipyparser-0.1.0.dist-info/LICENSE.md
minipyparser-0.1.0.dist-info/METADATA
minipyparser-0.1.0.dist-info/WHEEL
minipyparser-0.1.0.dist-info/top_level.txt
minipyparser-0.1.0.dist-info/RECORD
