Metadata-Version: 2.1
Name: minipyparser
Version: 0.1.0
Summary: A minimal python parser, written in python
Home-page: https://github.com/mguinhos/MiniPyParser
Author: Marcel Guinhos
Author-email: mguinhos@gmail.com
Requires-Python: >=3.6
License-File: LICENSE.md
